{
	"elements": [{
		"id": "mails",
		"type": "ifml.Layout",
		"attributes": {
			"name": "Mails",
			"default": true,
			"landmark": false,
			"xor": false,
			"width": "match_parent",
			"height": "match_parent",
			"orientation": "vertical",
			"thisLeft_toRightOf": "none",
        	"thisLeft_toLeftOf": "none",
        	"thisRight_toRightOf": "none",
        	"thisRight_toLeftOf": "none",
        	"thisTop_toTopOf": "none",
        	"thisTop_toBottomOf": "none",
        	"thisBottom_toBottomOf": "none",
        	"thisBottom_toTopOf": "none"
		},
		"metadata": {
			"graphics": {
				"position": {
					"x": 750,
					"y": -700
				},
				"size": {
					"width": 180,
					"height": 100
				}
			}
		}
	}],
	"relations": []
}